ocflcore/__init__.py
ocflcore/errors.py
ocflcore/stream.py
ocflcore/version.py
ocflcore/domain/__init__.py
ocflcore/domain/builder.py
ocflcore/domain/ocflobj.py
ocflcore/domain/root.py
ocflcore/domain/layouts/__init__.py
ocflcore/domain/layouts/base.py
ocflcore/domain/layouts/toplevel.py
ocflcore/persistence/__init__.py
ocflcore/persistence/commands.py
ocflcore/persistence/inventory.py
ocflcore/persistence/repository.py
ocflcore/persistence/transaction.py
ocflcore/persistence/workspace.py
ocflcore/persistence/storage/__init__.py
ocflcore/persistence/storage/base.py
ocflcore/persistence/storage/filesystem.py
ocflcore-0.1.0.dist-info/AUTHORS.rst
ocflcore-0.1.0.dist-info/LICENSE
ocflcore-0.1.0.dist-info/METADATA
ocflcore-0.1.0.dist-info/WHEEL
ocflcore-0.1.0.dist-info/top_level.txt
ocflcore-0.1.0.dist-info/RECORD
