Metadata-Version: 2.1
Name: ocflcore
Version: 0.1.0
Summary: Oxford Common Filesystem Layout module for Python.
Home-page: https://github.com/inveniosoftware/ocflcore
Author: CERN & Data Futures
Author-email: info@inveniosoftware.org
License: MIT
Keywords: OCFL package for Python.
Platform: any
Classifier: Intended Audience :: Developers
Classifier: License :: OSI Approved :: MIT License
Classifier: Operating System :: OS Independent
Classifier: Programming Language :: Python
Classifier: Topic :: Software Development :: Libraries :: Python Modules
Classifier: Programming Language :: Python :: 3
Classifier: Programming Language :: Python :: 3.6
Classifier: Programming Language :: Python :: 3.7
Classifier: Programming Language :: Python :: 3.8
Classifier: Programming Language :: Python :: 3.9
Classifier: Programming Language :: Python :: 3.10
Classifier: Development Status :: 1 - Planning
License-File: LICENSE
License-File: AUTHORS.rst
Provides-Extra: all
Requires-Dist: Sphinx (==4.2.0) ; extra == 'all'
Requires-Dist: black (>=21.12b0) ; extra == 'all'
Requires-Dist: check-manifest (>=0.42) ; extra == 'all'
Requires-Dist: coverage (<6,>=5.3) ; extra == 'all'
Requires-Dist: pytest-cov (>=2.10.1) ; extra == 'all'
Requires-Dist: pytest-isort (>=1.2.0) ; extra == 'all'
Requires-Dist: pytest-pycodestyle (>=2.2.0) ; extra == 'all'
Requires-Dist: pytest-pydocstyle (>=2.2.0) ; extra == 'all'
Requires-Dist: pytest (<7,>=6) ; extra == 'all'
Provides-Extra: docs
Requires-Dist: Sphinx (==4.2.0) ; extra == 'docs'
Provides-Extra: tests
Requires-Dist: black (>=21.12b0) ; extra == 'tests'
Requires-Dist: check-manifest (>=0.42) ; extra == 'tests'
Requires-Dist: coverage (<6,>=5.3) ; extra == 'tests'
Requires-Dist: pytest-cov (>=2.10.1) ; extra == 'tests'
Requires-Dist: pytest-isort (>=1.2.0) ; extra == 'tests'
Requires-Dist: pytest-pycodestyle (>=2.2.0) ; extra == 'tests'
Requires-Dist: pytest-pydocstyle (>=2.2.0) ; extra == 'tests'
Requires-Dist: pytest (<7,>=6) ; extra == 'tests'
